MANIFEST.in
setup.py
plutonium_plugin_configui_web/__init__.py
plutonium_plugin_configui_web/config.py
plutonium_plugin_configui_web/crud.py
plutonium_plugin_configui_web/http_handler.py
plutonium_plugin_configui_web/http_server.py
plutonium_plugin_configui_web/lang.py
plutonium_plugin_configui_web/models.py
plutonium_plugin_configui_web/plugin_config.py
plutonium_plugin_configui_web/structed_data_validator.py
plutonium_plugin_configui_web/version.py
plutonium_plugin_configui_web/widgets.py
plutonium_plugin_configui_web.egg-info/PKG-INFO
plutonium_plugin_configui_web.egg-info/SOURCES.txt
plutonium_plugin_configui_web.egg-info/dependency_links.txt
plutonium_plugin_configui_web.egg-info/requires.txt
plutonium_plugin_configui_web.egg-info/top_level.txt
plutonium_plugin_configui_web/languages/en.json
plutonium_plugin_configui_web/languages/hu.json
plutonium_plugin_configui_web/wwwroot/index.html
plutonium_plugin_configui_web/wwwroot/css/app.css
plutonium_plugin_configui_web/wwwroot/js/app.js
plutonium_plugin_configui_web/wwwroot/js/models.js
plutonium_plugin_configui_web/wwwroot/js/sqlchemyforms.validators.js
plutonium_plugin_configui_web/wwwroot/js/sqlchemyforms.widgets.js
plutonium_plugin_configui_web/wwwroot/pic/de.png
plutonium_plugin_configui_web/wwwroot/pic/en.png
plutonium_plugin_configui_web/wwwroot/pic/fr.png
plutonium_plugin_configui_web/wwwroot/pic/hu.png
plutonium_plugin_configui_web/wwwroot/sqlchemyforms/.git
plutonium_plugin_configui_web/wwwroot/sqlchemyforms/README.md
plutonium_plugin_configui_web/wwwroot/sqlchemyforms/css/bootstrap-dialog.min.css
plutonium_plugin_configui_web/wwwroot/sqlchemyforms/css/bootstrap-select.min.css
plutonium_plugin_configui_web/wwwroot/sqlchemyforms/css/bootstrap-switch.min.css
plutonium_plugin_configui_web/wwwroot/sqlchemyforms/css/bootstrap.min.css
plutonium_plugin_configui_web/wwwroot/sqlchemyforms/fonts/glyphicons-halflings-regular.eot
plutonium_plugin_configui_web/wwwroot/sqlchemyforms/fonts/glyphicons-halflings-regular.svg
plutonium_plugin_configui_web/wwwroot/sqlchemyforms/fonts/glyphicons-halflings-regular.ttf
plutonium_plugin_configui_web/wwwroot/sqlchemyforms/fonts/glyphicons-halflings-regular.woff
plutonium_plugin_configui_web/wwwroot/sqlchemyforms/js/base.js
