Metadata-Version: 1.0
Name: plutonium-plugin-configui-web
Version: 1.1.0
Summary: Web based config user interface plugin for Plutonium
Home-page: https://github.com/voidpp/plutonium-plugin-configui-web
Author: Lajos Santa
Author-email: santa.lajos@coldline.hu
License: MIT
Platform: UNKNOWN
